ratatouille/__init__.py
ratatouille/__main__.py
ratatouille/ratatouille.py
ratatouille/version.py
ratatouille-0.1.2.dist-info/METADATA
ratatouille-0.1.2.dist-info/WHEEL
ratatouille-0.1.2.dist-info/entry_points.txt
ratatouille-0.1.2.dist-info/top_level.txt
ratatouille-0.1.2.dist-info/RECORD
