Metadata-Version: 2.1
Name: ratatouille
Version: 0.1.2
Summary: System usage monitoring tool
Home-page: https://github.com/Ezibenroc/ratatouille
Author: Tom Cornebize
Author-email: tom.cornebize@gmail.com
License: MIT
Classifier: License :: OSI Approved :: MIT License
Classifier: Intended Audience :: Science/Research
Classifier: Intended Audience :: System Administrators
Classifier: Operating System :: POSIX :: Linux
Classifier: Programming Language :: Python :: 3.7
Classifier: Programming Language :: Python :: 3.8
Classifier: Programming Language :: Python :: 3.9
Classifier: Programming Language :: Python :: 3.10
Classifier: Programming Language :: Python :: 3.11
Requires-Dist: psutil >=5.8.0
